pm5/__init__.py
pm5/argparsers/pm5.py
pm5/pm5.py
pm5/requirements.txt
pm5-0.1.4.dist-info/LICENSE
pm5-0.1.4.dist-info/METADATA
pm5-0.1.4.dist-info/WHEEL
pm5-0.1.4.dist-info/entry_points.txt
pm5-0.1.4.dist-info/RECORD
