Metadata-Version: 2.1
Name: pm5
Version: 0.1.4
Summary: Like pm2 but without node.js
License: MIT
Author: Michael Mohamed
Author-email: michaelm063089@gmail.com
Requires-Python: >=3.9,<4.0
Classifier: License :: OSI Approved :: MIT License
Classifier: Programming Language :: Python :: 3
Classifier: Programming Language :: Python :: 3.9
Classifier: Programming Language :: Python :: 3.10
Classifier: Programming Language :: Python :: 3.11
Classifier: Programming Language :: Python :: 3.12
Requires-Dist: loguru (>=0.7.2,<0.8.0)
Requires-Dist: python-daemon (>=3.0.1,<4.0.0)
